dh_potluck/__init__.py
dh_potluck/api_docs.py
dh_potluck/audit_log/__init__.py
dh_potluck/audit_log/commands.py
dh_potluck/audit_log/mixins.py
dh_potluck/audit_log/models.py
dh_potluck/audit_log/trigger_templates/audit_deletes.jinja2
dh_potluck/audit_log/trigger_templates/audit_inserts.jinja2
dh_potluck/audit_log/trigger_templates/audit_updates.jinja2
dh_potluck/auth.py
dh_potluck/celery/__init__.py
dh_potluck/celery/crontab_parser.py
dh_potluck/celery/limiter.py
dh_potluck/celery/signals.py
dh_potluck/celery/synchronization.py
dh_potluck/click.py
dh_potluck/database.py
dh_potluck/decorators.py
dh_potluck/email/__init__.py
dh_potluck/email/email_service.py
dh_potluck/email/mandrill_email_client.py
dh_potluck/environment.py
dh_potluck/extension.py
dh_potluck/feature_flags.py
dh_potluck/fields.py
dh_potluck/health_checks.py
dh_potluck/image_api.py
dh_potluck/logging.py
dh_potluck/media_download.py
dh_potluck/messaging/__init__.py
dh_potluck/messaging/batching_consumer.py
dh_potluck/messaging/batching_message_consumer_app.py
dh_potluck/messaging/constants.py
dh_potluck/messaging/consumer.py
dh_potluck/messaging/exceptions.py
dh_potluck/messaging/message.py
dh_potluck/messaging/message_consumer_app.py
dh_potluck/messaging/message_envelope_schema.py
dh_potluck/messaging/producer.py
dh_potluck/messaging/typings.py
dh_potluck/messaging/utils.py
dh_potluck/mixpanel.py
dh_potluck/platform_connection.py
dh_potluck/queries_summary.py
dh_potluck/s3_service.py
dh_potluck/skeema/__init__.py
dh_potluck/skeema/commands.py
dh_potluck/sqlalchemy_decorators.py
dh_potluck/templates/redoc.html
dh_potluck/types/__init__.py
dh_potluck/types/json_serializable.py
dh_potluck/utils/__init__.py
dh_potluck/utils/datadog.py
dh_potluck/utils/ddtrace_compatibility.py
dh_potluck/utils/evaluator.py
dh_potluck/utils/term.py
dh_potluck/validators.py
dh_potluck-1.38.0.dist-info/METADATA
dh_potluck-1.38.0.dist-info/WHEEL
dh_potluck-1.38.0.dist-info/RECORD
