Metadata-Version: 2.3
Name: dh-potluck
Version: 1.38.0
Summary: 
Requires-Python: >=3.10,<4.0
Classifier: Programming Language :: Python :: 3
Classifier: Programming Language :: Python :: 3.10
Classifier: Programming Language :: Python :: 3.11
Classifier: Programming Language :: Python :: 3.12
Classifier: Programming Language :: Python :: 3.13
Requires-Dist: boltons (>=20.2.1,<21.0.0)
Requires-Dist: boto3 (>=1.40.32,<2.0.0)
Requires-Dist: confluent-kafka (>=2.11.1,<2.12.0)
Requires-Dist: ddtrace (>=2.5.3,<=4.3.0)
Requires-Dist: flask (>=3.0.2,<4.0.0)
Requires-Dist: flask-limiter (>=2.7.0,<3.0.0)
Requires-Dist: flask-redis (>=0.4.0,<0.5.0)
Requires-Dist: flask-smorest (<1.0.0)
Requires-Dist: flask-sqlalchemy (>=3.0.0,<4.0.0)
Requires-Dist: json-log-formatter (>=0.3.0,<0.4.0)
Requires-Dist: launchdarkly-server-sdk (>=9.13.1,<10.0.0)
Requires-Dist: mailchimp-transactional (>=1.0.56,<1.1.0)
Requires-Dist: marshmallow (>=3.18.0,<4.0.0)
Requires-Dist: mixpanel (>=4.10.0,<5.0.0)
Requires-Dist: mysqlclient (>=2.0,<3.0)
Requires-Dist: puremagic (>=1.30,<2.0)
Requires-Dist: requests (>=2.32.4,<3.0.0)
Requires-Dist: sqlalchemy (>=1.4.45,<3.0.0)
Requires-Dist: werkzeug (>=3.1.5,<4.0.0)
